MANIFEST.in
hr_timesheet_invoice_data.xml
hr_timesheet_invoice_demo.xml
hr_timesheet_invoice_report.xml
hr_timesheet_invoice_view.xml
hr_timesheet_invoice_wizard.xml
setup.py
./__init__.py
./__openerp__.py
./hr_timesheet_invoice.py
./report/__init__.py
./report/account_analytic_profit.py
./report/hr_timesheet_invoice_report.py
./report/report_analytic.py
./wizard/__init__.py
./wizard/hr_timesheet_analytic_profit.py
./wizard/hr_timesheet_final_invoice_create.py
./wizard/hr_timesheet_invoice_create.py
i18n/ar.po
i18n/bg.po
i18n/bs.po
i18n/ca.po
i18n/cs.po
i18n/da.po
i18n/de.po
i18n/el.po
i18n/es.po
i18n/es_AR.po
i18n/es_CR.po
i18n/es_EC.po
i18n/es_MX.po
i18n/es_VE.po
i18n/et.po
i18n/fi.po
i18n/fr.po
i18n/hr.po
i18n/hr_timesheet_invoice.pot
i18n/hu.po
i18n/id.po
i18n/it.po
i18n/ja.po
i18n/ko.po
i18n/lt.po
i18n/lv.po
i18n/mk.po
i18n/mn.po
i18n/nl.po
i18n/nl_BE.po
i18n/pl.po
i18n/pt.po
i18n/pt_BR.po
i18n/ro.po
i18n/ru.po
i18n/sl.po
i18n/sq.po
i18n/sr@latin.po
i18n/sv.po
i18n/tlh.po
i18n/tr.po
i18n/uk.po
i18n/vi.po
i18n/zh_CN.po
i18n/zh_TW.po
images/hr_bill_task_work.jpeg
images/hr_type_of_invoicing.jpeg
openerp_hr_timesheet_invoice.egg-info/PKG-INFO
openerp_hr_timesheet_invoice.egg-info/SOURCES.txt
openerp_hr_timesheet_invoice.egg-info/dependency_links.txt
openerp_hr_timesheet_invoice.egg-info/requires.txt
openerp_hr_timesheet_invoice.egg-info/top_level.txt
report/account_analytic_profit.rml
report/account_analytic_profit.sxw
report/hr_timesheet_invoice_report_view.xml
report/report_analytic_view.xml
security/ir.model.access.csv
test/hr_timesheet_invoice_report.yml
test/test_hr_timesheet_invoice.yml
test/test_hr_timesheet_invoice_no_prod_tax.yml
wizard/hr_timesheet_analytic_profit_view.xml
wizard/hr_timesheet_invoice_create_final_view.xml
wizard/hr_timesheet_invoice_create_view.xml